powerplay/__init__.py
powerplay/api_client.py
powerplay/configuration.py
powerplay/rest.py
powerplay/api/__init__.py
powerplay/api/conferences_api.py
powerplay/api/divisions_api.py
powerplay/api/draft_api.py
powerplay/api/games_api.py
powerplay/api/players_api.py
powerplay/api/schedule_api.py
powerplay/api/standings_api.py
powerplay/api/stats_api.py
powerplay/api/teams_api.py
powerplay/models/__init__.py
powerplay/models/any_of_game_content_media_epg_items.py
powerplay/models/conference.py
powerplay/models/conferences.py
powerplay/models/division.py
powerplay/models/division_conference.py
powerplay/models/divisions.py
powerplay/models/draft.py
powerplay/models/draft_drafts.py
powerplay/models/draft_picks.py
powerplay/models/draft_prospect.py
powerplay/models/draft_prospect_amateur_league.py
powerplay/models/draft_prospect_amateur_team.py
powerplay/models/draft_prospect_primary_position.py
powerplay/models/draft_prospect_prospect_category.py
powerplay/models/draft_prospects.py
powerplay/models/draft_rounds.py
powerplay/models/draft_team.py
powerplay/models/error.py
powerplay/models/franchise.py
powerplay/models/game.py
powerplay/models/game_boxscore.py
powerplay/models/game_boxscore_team.py
powerplay/models/game_boxscore_team_coaches.py
powerplay/models/game_boxscore_team_on_ice_plus.py
powerplay/models/game_boxscore_team_person.py
powerplay/models/game_boxscore_team_players.py
powerplay/models/game_boxscore_team_players_person.py
powerplay/models/game_boxscore_team_players_position.py
powerplay/models/game_boxscore_team_players_stats.py
powerplay/models/game_boxscore_team_players_stats_skater_stats.py
powerplay/models/game_boxscore_team_position.py
powerplay/models/game_boxscore_team_team.py
powerplay/models/game_boxscore_team_team_stats.py
powerplay/models/game_boxscore_team_team_stats_team_skater_stats.py
powerplay/models/game_boxscore_teams.py
powerplay/models/game_boxscores.py
powerplay/models/game_content.py
powerplay/models/game_content_editorial.py
powerplay-0.0.1.dist-info/METADATA
powerplay-0.0.1.dist-info/WHEEL
powerplay-0.0.1.dist-info/top_level.txt
powerplay-0.0.1.dist-info/RECORD
