Metadata-Version: 2.1
Name: powerplay
Version: 0.0.1
Summary: Functions to Access Hockey Play by Play Data from the NHL API
Home-page: http://www.github.com/saiemgilani/powerplay
Author: Saiem Gilani
Author-email: saiem.gilani@gmail.com
Maintainer: Saiem Gilani
License: MIT
Keywords: Swagger,NHL API
Platform: UNKNOWN
Classifier: Development Status :: 3 - Alpha
Classifier: Intended Audience :: Developers
Classifier: Topic :: Software Development :: Libraries
Classifier: License :: OSI Approved :: MIT License
Classifier: Programming Language :: Python :: 3
Classifier: Programming Language :: Python :: 3.6
Classifier: Programming Language :: Python :: 3.7
Classifier: Programming Language :: Python :: 3.8
Classifier: Programming Language :: Python :: 3.9
Requires-Dist: urllib3 (>=1.15)
Requires-Dist: six (>=1.10)
Requires-Dist: certifi
Requires-Dist: python-dateutil
Requires-Dist: numpy (>=1.13.0)
Requires-Dist: pandas (>=1.0.3)
Requires-Dist: beautifulsoup4 (>=4.4.0)
Requires-Dist: requests (>=2.18.1)
Requires-Dist: lxml (>=4.2.1)
Requires-Dist: pyarrow (>=1.0.1)
Requires-Dist: pygithub (>=1.51)
Requires-Dist: scipy (>=1.4.0)
Requires-Dist: matplotlib (>=2.0.0)
Requires-Dist: tqdm (>=4.50.0)
Requires-Dist: attrs (>=20.3.0)
